Metadata-Version: 1.0
Name: BytecodeAssembler
Version: 0.3
Summary: Generate Python code objects by "assembling" bytecode (Now includes a functional/AST-oriented API, too!)
Home-page: http://pypi.python.org/pypi/BytecodeAssembler
Author: Phillip J. Eby
Author-email: peak@eby-sarna.com
License: PSF or ZPL
Platform: UNKNOWN
